rtsvg/__init__.py
rtsvg/circle_packer.py
rtsvg/convey_proximity_layout.py
rtsvg/mds_at_scale.py
rtsvg/polars_force_directed_layout.py
rtsvg/polars_spring_layout.py
rtsvg/polars_spring_layout_opt.py
rtsvg/rt_annotations_mixin.py
rtsvg/rt_art_mixin.py
rtsvg/rt_boxplot_mixin.py
rtsvg/rt_calendarheatmap_mixin.py
rtsvg/rt_chord_diagram_mixin.py
rtsvg/rt_choroplethmap_mixin.py
rtsvg/rt_color_manager.py
rtsvg/rt_component.py
rtsvg/rt_coordinated_views.py
rtsvg/rt_datamanip_mixin.py
rtsvg/rt_entity_position.py
rtsvg/rt_geomaps_mixin.py
rtsvg/rt_geometry_mixin.py
rtsvg/rt_graph_interactive_panel.py
rtsvg/rt_graph_layouts_mixin.py
rtsvg/rt_histogram_mixin.py
rtsvg/rt_json_mixin.py
rtsvg/rt_layouts_mixin.py
rtsvg/rt_link_mixin.py
rtsvg/rt_linknode_mixin.py
rtsvg/rt_linknodeshortest_mixin.py
rtsvg/rt_ontologies_mixin.py
rtsvg/rt_panel_mixin.py
rtsvg/rt_periodic_barchart_mixin.py
rtsvg/rt_piechart_mixin.py
rtsvg/rt_shapes_mixin.py
rtsvg/rt_small_multiples_mixin.py
rtsvg/rt_spreadlines_interactive_panel.py
rtsvg/rt_spreadlines_mixin.py
rtsvg/rt_stackable.py
rtsvg/rt_temporal_barchart_mixin.py
rtsvg/rt_text_mixin.py
rtsvg/rt_timeline_mixin.py
rtsvg/rt_wordcloud_mixin.py
rtsvg/rt_xy_mixin.py
rtsvg/rtsvg.py
rtsvg/scu_editor_panel.py
rtsvg/scu_pyramid_method_diagram.py
rtsvg/udist_scatterplots_via_sectors_tile_opt.py
rtsvg/config/20230628_times_serif_14.txt
rtsvg/config/20230628_times_serif_16.txt
rtsvg/config/20230629_ariel_14.txt
rtsvg/config/20230629_ariel_16.txt
rtsvg/config/cividis.rgb
rtsvg/config/simple_graph_df.csv
rtsvg/config/simple_graph_layouts.csv
rtsvg/config/udist_scatterplots_via_sectors_tile_opt.parquet
rtsvg/laguerre_voronoi_2d/LICENSE.md
rtsvg/laguerre_voronoi_2d/README.md
rtsvg/laguerre_voronoi_2d/__init__.py
rtsvg/laguerre_voronoi_2d/laguerre_voronoi_2d.py
rtsvg/laguerre_voronoi_2d/original_source.txt
rtsvg-0.1.23.20251105.dist-info/METADATA
rtsvg-0.1.23.20251105.dist-info/WHEEL
rtsvg-0.1.23.20251105.dist-info/licenses/LICENSE
rtsvg-0.1.23.20251105.dist-info/RECORD
