Metadata-Version: 2.4
Name: rtsvg
Version: 0.1.23.20251105
Summary: Visualization Package Leveraging SVG in Jupyter Notebooks
Project-URL: Homepage, https://github.com/datrcode/racetrack_svg_framework
Project-URL: Repository, https://github.com/datrcode/racetrack_svg_framework
Author-email: "D. Trimm" <dave.trimm+rtsvg@gmail.com>
License:                                  Apache License
License-File: LICENSE
Classifier: License :: OSI Approved :: Apache Software License
Classifier: Operating System :: OS Independent
Classifier: Programming Language :: Python :: 3
Requires-Python: >=3.8
Requires-Dist: geopandas
Requires-Dist: hdbscan
Requires-Dist: jupyter-bokeh
Requires-Dist: networkx
Requires-Dist: numpy
Requires-Dist: pandas
Requires-Dist: panel
Requires-Dist: polars
Requires-Dist: pyarrow
Requires-Dist: pyperclip
Requires-Dist: scikit-learn
Requires-Dist: scipy
Requires-Dist: shapely
Requires-Dist: squarify
Requires-Dist: svglib
Requires-Dist: umap-learn
Requires-Dist: wordcloud
